src/__init__.py
src/operations.py
calculadora_do_lucas-0.1.0.dist-info/METADATA
calculadora_do_lucas-0.1.0.dist-info/WHEEL
calculadora_do_lucas-0.1.0.dist-info/top_level.txt
calculadora_do_lucas-0.1.0.dist-info/RECORD
