Metadata-Version: 2.4
Name: calculadora_do_Lucas
Version: 0.1.0
Summary: Biblioteca de operações matemáticas básicas em Python.
Home-page: https://github.com/LucasMarianiG/Lib_Calculadora.git
Author: Lucas Mariani Gomes
Author-email: lucas2607.gomes@gmail.com
Classifier: Programming Language :: Python :: 3
Classifier: License :: OSI Approved :: MIT License
Classifier: Operating System :: OS Independent
Requires-Python: >=3.8
Dynamic: author
Dynamic: author-email
Dynamic: classifier
Dynamic: description
Dynamic: description-content-type
Dynamic: home-page
Dynamic: requires-python
Dynamic: summary
